{
    "Home": "D:\\program_files\\xampp\\htdocs\\CharonMVC\\app\\controller\\Home.php",
    "Charon": "D:\\program_files\\xampp\\htdocs\\CharonMVC\\system\\core\\app.php",
    "Charon\\CLI": "D:\\program_files\\xampp\\htdocs\\CharonMVC\\system\\core\\cli.php",
    "Config": "D:\\program_files\\xampp\\htdocs\\CharonMVC\\system\\core\\config.php",
    "Controller": "D:\\program_files\\xampp\\htdocs\\CharonMVC\\system\\core\\controller.php",
    "Load": "D:\\program_files\\xampp\\htdocs\\CharonMVC\\system\\core\\load.php",
    "Route": "D:\\program_files\\xampp\\htdocs\\CharonMVC\\system\\core\\route.php",
    "Request": "D:\\program_files\\xampp\\htdocs\\CharonMVC\\system\\core\\http\\request.php",
    "Response": "D:\\program_files\\xampp\\htdocs\\CharonMVC\\system\\core\\http\\response.php",
    "Charon\\Benchmark": "D:\\program_files\\xampp\\htdocs\\CharonMVC\\system\\libs\\benchmark.php",
    "Charon\\Dump": "D:\\program_files\\xampp\\htdocs\\CharonMVC\\system\\libs\\dump.php",
    "Charon\\IP": "D:\\program_files\\xampp\\htdocs\\CharonMVC\\system\\libs\\ip.php",
    "Charon\\License": "D:\\program_files\\xampp\\htdocs\\CharonMVC\\system\\libs\\license.php",
    "Charon\\NoCSRF": "D:\\program_files\\xampp\\htdocs\\CharonMVC\\system\\libs\\nocsrf.php",
    "Session": "D:\\program_files\\xampp\\htdocs\\CharonMVC\\system\\libs\\session.php",
    "Capella": "D:\\program_files\\xampp\\htdocs\\CharonMVC\\system\\libs\\capella\\capella.php",
    "Charon\\Captcha": "D:\\program_files\\xampp\\htdocs\\CharonMVC\\system\\libs\\captcha\\captcha.php",
    "SVGCaptcha": "D:\\program_files\\xampp\\htdocs\\CharonMVC\\system\\libs\\captcha\\svgcaptcha.php",
    "Point": "D:\\program_files\\xampp\\htdocs\\CharonMVC\\system\\libs\\captcha\\svgcaptcha.php",
    "Charon\\oops": "D:\\program_files\\xampp\\htdocs\\CharonMVC\\system\\libs\\oops\\oops.php",
    "Puck": "D:\\program_files\\xampp\\htdocs\\CharonMVC\\system\\libs\\puck\\puck.php",
    "Charon\\Validator": "D:\\program_files\\xampp\\htdocs\\CharonMVC\\system\\libs\\validator\\validator.php"
}